cedardb/__init__.py
cedardb/client.py
cedardb/response.py
cedardb/types.py
cedardb-0.0.6.dist-info/licenses/LICENSE.md
cedardb-0.0.6.dist-info/METADATA
cedardb-0.0.6.dist-info/WHEEL
cedardb-0.0.6.dist-info/top_level.txt
cedardb-0.0.6.dist-info/RECORD
