Metadata-Version: 2.4
Name: cedardb
Version: 0.0.6
Summary: Pythonic driver for CedarDB
Author-email: Ivan <surister98@gmail.com>
License: Copyright 2025 github.com/surister
Project-URL: Home Page, https://github.com/surister/cedardb-python
Project-URL: DOCUMENTATION, https://github.com/surister/cedardb-python
Project-URL: Repository, https://github.com/surister/cedardb-python.git
Project-URL: GitHub, https://github.com/surister/cedardb-python
Project-URL: Changelog, https://github.com/surister/cedardb-python/releases
Keywords: cedardb,driver,connector,database,psycopg
Classifier: Topic :: Database
Classifier: Topic :: Database :: Front-Ends
Classifier: Natural Language :: English
Classifier: Intended Audience :: Developers
Classifier: License :: OSI Approved :: MIT License
Classifier: Operating System :: OS Independent
Classifier: Programming Language :: Python
Classifier: Programming Language :: Python :: 3
Classifier: Programming Language :: Python :: 3 :: Only
Requires-Python: >=3.11
License-File: LICENSE.md
Requires-Dist: psycopg>=3.2.9
Dynamic: license-file
